estnltk/common.py
estnltk/resource_utils.py
estnltk/text.py
estnltk/__init__.py
estnltk/downloader.py
estnltk/default_resolver.py
estnltk/storage/__init__.py
estnltk/storage/sqlite/collection.py
estnltk/storage/sqlite/__init__.py
estnltk/storage/postgres/collection_meta.py
estnltk/storage/postgres/storage.py
estnltk/storage/postgres/collection_meta_selection.py
estnltk/storage/postgres/subcollection.py
estnltk/storage/postgres/pg_operations.py
estnltk/storage/postgres/collection.py
estnltk/storage/postgres/__init__.py
estnltk/storage/postgres/subcollectionfragments.py
estnltk/storage/postgres/subcollectionlayer.py
estnltk/storage/postgres/iterators.py
estnltk/storage/postgres/pgpass_parsing.py
estnltk/storage/postgres/storage_collections.py
estnltk/storage/postgres/sql_composition/from_clause.py
estnltk/storage/postgres/sql_composition/__init__.py
estnltk/storage/postgres/sql_composition/where_clause.py
estnltk/storage/postgres/sql_composition/selected_columns.py
estnltk/storage/postgres/sql_composition/sql_table_naming.py
estnltk/storage/postgres/tests/test_pgcollection_export_layer.py
estnltk/storage/postgres/tests/test_pgcollection_store_syntax_layer.py
estnltk/storage/postgres/tests/test_metadata_query.py
estnltk/storage/postgres/tests/test_buffered_insert.py
estnltk/storage/postgres/tests/test_pgsubcollection_permutate.py
estnltk/storage/postgres/tests/test_missing_layer_query.py
estnltk/storage/postgres/tests/test_pgcollection_store_relation_layer.py
estnltk/storage/postgres/tests/test_pgsubcollection.py
estnltk/storage/postgres/tests/test_pgcollection_detached_layer.py
estnltk/storage/postgres/tests/test_.py
estnltk/storage/postgres/tests/test_pgcollection_hide_documents.py
estnltk/storage/postgres/tests/test_keys_query.py
estnltk/storage/postgres/tests/test_layer_ngram_query.py
estnltk/storage/postgres/tests/__init__.py
estnltk/storage/postgres/tests/test_pgcollection_meta_selection.py
estnltk-1.7.4.dist-info/METADATA
estnltk-1.7.4.dist-info/RECORD
estnltk-1.7.4.dist-info/top_level.txt
estnltk-1.7.4.dist-info/WHEEL
estnltk-1.7.4.dist-info/LICENSE
