Metadata-Version: 2.2
Name: estnltk
Version: 1.7.4
Summary: EstNLTK — open source tools for Estonian natural language processing
Home-page: https://github.com/estnltk/estnltk
Author: University of Tartu
Author-email: Siim Orasmaa <siim.orasmaa@ut.ee>, Sven Laur <swen@math.ut.ee>, Paul Tammo <paul.tammo@gmail.com>
License: Dual License: GPL-2.0 OR Apache-2.0
Project-URL: homepage, https://github.com/estnltk/estnltk
Project-URL: documentation, https://github.com/estnltk/estnltk/tree/main/tutorials
Project-URL: repository, https://github.com/estnltk/estnltk/tree/main/estnltk
Project-URL: changelog, https://github.com/estnltk/estnltk/blob/main/CHANGELOG.md
Keywords: Estonian natural language processing,Estonian linguistic processing
Classifier: Intended Audience :: Developers
Classifier: Intended Audience :: Education
Classifier: Intended Audience :: Science/Research
Classifier: Intended Audience :: Information Technology
Classifier: Operating System :: OS Independent
Classifier: Programming Language :: Python :: 3.9
Classifier: Programming Language :: Python :: 3.10
Classifier: Programming Language :: Python :: 3.11
Classifier: Programming Language :: Python :: 3.12
Classifier: Programming Language :: Python :: 3.13
Classifier: Topic :: Scientific/Engineering
Classifier: Topic :: Scientific/Engineering :: Artificial Intelligence
Classifier: Topic :: Scientific/Engineering :: Information Analysis
Classifier: Topic :: Text Processing
Classifier: Topic :: Text Processing :: Linguistic
Requires-Python: >=3.9
License-File: LICENSE
Requires-Dist: estnltk-core>=1.7.4
Requires-Dist: nltk>=3.4.1
Requires-Dist: regex>=2015.07.19
Requires-Dist: python-crfsuite>=0.8.3
Requires-Dist: cached-property>=1.2.0
Requires-Dist: bs4
Requires-Dist: html5lib
Requires-Dist: lxml
Requires-Dist: networkx
Requires-Dist: matplotlib
Requires-Dist: requests
Requires-Dist: tqdm
Requires-Dist: ipython
Requires-Dist: conllu
Requires-Dist: pandas
Requires-Dist: pyahocorasick
Requires-Dist: packaging
Provides-Extra: tests
Requires-Dist: pytest; extra == "tests"
Requires-Dist: pytest-httpserver; extra == "tests"
Provides-Extra: collocation-net
Requires-Dist: scikit-learn; extra == "collocation-net"
Provides-Extra: downloader
Requires-Dist: huggingface-hub; extra == "downloader"
Provides-Extra: postgresql
Requires-Dist: psycopg2; extra == "postgresql"
Dynamic: home-page
